odoo/addons/stock_search_supplierinfo_code/README.rst
odoo/addons/stock_search_supplierinfo_code/__init__.py
odoo/addons/stock_search_supplierinfo_code/__manifest__.py
odoo/addons/stock_search_supplierinfo_code/i18n/it.po
odoo/addons/stock_search_supplierinfo_code/i18n/stock_search_supplierinfo_code.pot
odoo/addons/stock_search_supplierinfo_code/readme/CONTRIBUTORS.rst
odoo/addons/stock_search_supplierinfo_code/readme/DESCRIPTION.rst
odoo/addons/stock_search_supplierinfo_code/static/description/icon.png
odoo/addons/stock_search_supplierinfo_code/static/description/index.html
odoo/addons/stock_search_supplierinfo_code/views/stock_picking.xml
odoo14_addon_stock_search_supplierinfo_code-14.0.1.0.1.dev6.dist-info/METADATA
odoo14_addon_stock_search_supplierinfo_code-14.0.1.0.1.dev6.dist-info/WHEEL
odoo14_addon_stock_search_supplierinfo_code-14.0.1.0.1.dev6.dist-info/top_level.txt
odoo14_addon_stock_search_supplierinfo_code-14.0.1.0.1.dev6.dist-info/RECORD
